{
  "placeholderImages": [
    {
      "id": "hero-bg",
      "description": "Soft nature and wellness background",
      "imageUrl": "https://picsum.photos/seed/palmira-hero/1920/1080",
      "imageHint": "nature wellness"
    },
    {
      "id": "about-me",
      "description": "Professional portrait of a beauty guide",
      "imageUrl": "https://picsum.photos/seed/palmira-profile/600/800",
      "imageHint": "professional woman"
    },
    {
      "id": "limelife-card",
      "description": "High-end skincare and makeup products",
      "imageUrl": "https://picsum.photos/seed/limelife/800/600",
      "imageHint": "skincare makeup"
    },
    {
      "id": "ringana-card",
      "description": "Fresh natural cosmetics",
      "imageUrl": "https://picsum.photos/seed/ringana/800/600",
      "imageHint": "natural cosmetics"
    },
    {
      "id": "promo-1",
      "description": "Wellness promotion banner",
      "imageUrl": "https://picsum.photos/seed/promo1/800/400",
      "imageHint": "spa beauty"
    },
    {
      "id": "post-1",
      "description": "Skincare routine blog post",
      "imageUrl": "https://picsum.photos/seed/post1/600/400",
      "imageHint": "skincare routine"
    },
    {
      "id": "post-2",
      "description": "Natural ingredients blog post",
      "imageUrl": "https://picsum.photos/seed/post2/600/400",
      "imageHint": "herbal ingredients"
    },
    {
      "id": "ll-novedades",
      "description": "New products arrivals",
      "imageUrl": "https://picsum.photos/seed/ll-new/600/600",
      "imageHint": "cosmetic new"
    },
    {
      "id": "ll-sales",
      "description": "Birthday sales and offers",
      "imageUrl": "https://picsum.photos/seed/ll-sale/600/600",
      "imageHint": "beauty discount"
    },
    {
      "id": "ll-maquillaje",
      "description": "Professional makeup products",
      "imageUrl": "https://picsum.photos/seed/ll-makeup/600/600",
      "imageHint": "makeup brush"
    },
    {
      "id": "ll-piel",
      "description": "Skincare collection",
      "imageUrl": "https://picsum.photos/seed/ll-skin/600/600",
      "imageHint": "skincare cream"
    },
    {
      "id": "ll-cabello",
      "description": "Hair care products",
      "imageUrl": "https://picsum.photos/seed/ll-hair/600/600",
      "imageHint": "hair care"
    },
    {
      "id": "ll-colecciones",
      "description": "Full beauty collections",
      "imageUrl": "https://picsum.photos/seed/ll-col/600/600",
      "imageHint": "beauty kit"
    },
    {
      "id": "ll-icons",
      "description": "Iconic products",
      "imageUrl": "https://picsum.photos/seed/ll-icon/600/600",
      "imageHint": "luxury cosmetic"
    },
    {
      "id": "ll-unete",
      "description": "Join the LimeLife team",
      "imageUrl": "https://picsum.photos/seed/ll-join/600/600",
      "imageHint": "happy woman"
    }
  ]
}